main.py
source_box_data_extract/__init__.py
source_box_data_extract/box_api.py
source_box_data_extract/run.py
source_box_data_extract/schemas.py
source_box_data_extract/source.py
source_box_data_extract/spec.yaml
airbyte_source_box_data_extract-0.1.13.dist-info/METADATA
airbyte_source_box_data_extract-0.1.13.dist-info/WHEEL
airbyte_source_box_data_extract-0.1.13.dist-info/entry_points.txt
airbyte_source_box_data_extract-0.1.13.dist-info/RECORD
