Metadata-Version: 2.3
Name: airbyte-source-box-data-extract
Version: 0.1.13
Summary: Source implementation for Box File Text Extraction.
License: MIT
Author: Airbyte
Author-email: contact@airbyte.io
Requires-Python: >=3.11,<3.12
Classifier: License :: OSI Approved :: MIT License
Classifier: Programming Language :: Python :: 3
Classifier: Programming Language :: Python :: 3.11
Requires-Dist: airbyte-cdk (>=6,<7)
Requires-Dist: box-sdk-gen (>=1.11.1,<2.0.0)
Project-URL: Documentation, https://docs.airbyte.com/integrations/sources/box-files-text
Project-URL: Homepage, https://airbyte.com
Project-URL: Repository, https://github.com/airbytehq/airbyte
